vatrix/__init__.py
vatrix/main.py
vatrix/api/__init__.py
vatrix/api/receiver.py
vatrix/cli/__init__.py
vatrix/cli/args.py
vatrix/config/settings.py
vatrix/inputs/__init__.py
vatrix/inputs/file_reader.py
vatrix/inputs/stream_reader.py
vatrix/outputs/__init__.py
vatrix/outputs/file_writer.py
vatrix/outputs/gateway_writer.py
vatrix/outputs/rotating_writer.py
vatrix/outputs/sbert_writer.py
vatrix/pipeline/__init__.py
vatrix/pipeline/context_builder.py
vatrix/pipeline/embedding_pipeline.py
vatrix/pipeline/process_api_ingest.py
vatrix/pipeline/processor.py
vatrix/pipeline/stream_runner.py
vatrix/pipeline/unique_log_collector.py
vatrix/sample_logs/__init__.py
vatrix/sample_logs/input_logs.ndjson
vatrix/templates/__init__.py
vatrix/templates/loader.py
vatrix/templates/template_map.py
vatrix/templates/tmanager.py
vatrix/templates/dialog_logon/base_template.j2
vatrix/templates/dialog_logon/variation_1.j2
vatrix/templates/dialog_logon/variation_2.j2
vatrix/templates/dialog_logon/variation_3.j2
vatrix/templates/dialog_logon/variation_4.j2
vatrix/templates/dialog_logon/variation_5.j2
vatrix/utils/__init__.py
vatrix/utils/banner.py
vatrix/utils/embedding.py
vatrix/utils/logger.py
vatrix/utils/pathing.py
vatrix/utils/similarity.py
vatrix-0.2.1.dist-info/licenses/LICENSE
vatrix-0.2.1.dist-info/METADATA
vatrix-0.2.1.dist-info/WHEEL
vatrix-0.2.1.dist-info/entry_points.txt
vatrix-0.2.1.dist-info/top_level.txt
vatrix-0.2.1.dist-info/RECORD
